pylyric/__init__.py
pylyric/plot.py
pylyric_alpha-0.0.1.dist-info/LICENSE
pylyric_alpha-0.0.1.dist-info/METADATA
pylyric_alpha-0.0.1.dist-info/WHEEL
pylyric_alpha-0.0.1.dist-info/entry_points.txt
pylyric_alpha-0.0.1.dist-info/top_level.txt
pylyric_alpha-0.0.1.dist-info/RECORD
