Metadata-Version: 2.1
Name: pylyric-alpha
Version: 0.0.1
Summary: A package for sentimental analysis of a song
Home-page: https://github.com/aegon47/pylyric.git
Author: aeg0n
Author-email: chandu199827@gmail.com
License: UNKNOWN
Platform: UNKNOWN
Classifier: Programming Language :: Python :: 3
Classifier: License :: OSI Approved :: MIT License
Classifier: Operating System :: OS Independent
Requires-Python: >=3.6
Requires-Dist: algorithmia
